src/uart_tx.v
// uart_tx.v
// Troy Kaufman
// UART transmission module (Verilog version)

module uart_tx (
    input wire fpga_clk,       // fpga clk
    input wire nrst,           // inverted reset
    input wire tx_en,          // enable transmission
    input wire [7:0] din,      // one byte data input
    output wire sout,          // one bit data output
    output reg busy_tx
);

// FSM states
parameter IDLE = 2'b00;
parameter TX   = 2'b01;

reg [1:0] cs, ns;

parameter BAUDRATE = 115200;
reg [15:0] tick_total;       // number of FPGA clocks per bit
reg [15:0] tick_cnt;         // baud tick counter
reg [8:0] dout;              // shift register: start(0) + 8 data bits + stop(1)
reg tx_complete;
reg baud_clk;
reg baud_edge, baud_edge_d1, baud_edge_d2;
reg load;
reg [4:0] baud_cnt;
reg tx_en_d1, tx_en_d2, tx_en_posedge;

wire sout_data;

assign tick_total = 16'd5; // You may want to adjust based on fpga_clk

// tx_en edge detection logic
always @(posedge fpga_clk) begin
    if (~nrst) begin
        tx_en_d1 <= 1'b0;
        tx_en_d2 <= 1'b0;
        tx_en_posedge <= 1'b0;
    end else begin
        tx_en_d1 <= tx_en;
        tx_en_d2 <= tx_en_d1;
        if (tx_en_d1 && ~tx_en_d2)
            tx_en_posedge <= 1'b1;
        else
            tx_en_posedge <= 1'b0;
    end
end

// load signal logic
always @(posedge fpga_clk) begin
    if (~nrst)
        load <= 1'b0;
    else if (tx_en_posedge)
        load <= 1'b1;
    else
        load <= 1'b0;
end

// tick counter and baud edge generation
always @(posedge fpga_clk) begin
    if (~nrst || tx_en_posedge) begin
        tick_cnt <= 16'd0;
        baud_edge <= 1'b0;
    end else if (tick_cnt == tick_total) begin
        tick_cnt <= 16'd0;
        baud_edge <= 1'b1;
    end else begin
        tick_cnt <= tick_cnt + 1'b1;
        baud_edge <= 1'b0;
    end
end

// baud edge detection and baud clock pulse
always @(posedge fpga_clk) begin
    if (~nrst || tx_en_posedge) begin
        baud_edge_d1 <= 1'b0;
        baud_edge_d2 <= 1'b0;
        baud_clk <= 1'b0;
        baud_cnt <= 5'd0;
    end else begin
        baud_edge_d1 <= baud_edge;
        baud_edge_d2 <= baud_edge_d1;

        if (baud_edge_d1 && ~baud_edge_d2) begin
            baud_clk <= 1'b1;
            baud_cnt <= baud_cnt + 1'b1;
        end else if (baud_cnt > 5'd9) begin
            baud_clk <= baud_clk;
            baud_cnt <= 5'd0;
        end else begin
            baud_clk <= 1'b0;
            baud_cnt <= baud_cnt;
        end
    end
end

// PISO Shift Register and FSM update
always @(posedge fpga_clk) begin
    if (~nrst) begin
        dout <= 9'b111111111;
        cs <= IDLE;
    end else if (load) begin
        dout <= {1'b1, din}; // start bit is implicit with dout[0] = 0
        dout[8] <= 1'b0;     // start bit
        cs <= TX;
    end else if (baud_clk) begin
        dout <= {dout[7:0], 1'b1}; // shift in stop bits (high)
        cs <= TX;
    end
end

// FSM next state logic
always @(*) begin
    case (cs)
        IDLE: begin
            if (tx_en)
                ns = TX;
            else
                ns = IDLE;
        end
        TX: begin
            if (baud_cnt > 5'd9)
                ns = TX;
            else if (~tx_en)
                ns = IDLE;
            else
                ns = TX;
        end
        default: ns = IDLE;
    endcase
end

// Output assignments
assign sout_data = dout[8];
assign sout = sout_data;

endmodule

tb/uart_tx_tb.sv
// uart_tx_tb.v
// Troy Kaufman
// UART transmitter testbench

`timescale 1ns/1ns

module uart_tx_tb();
    logic fpga_clk;
    logic nrst;
    logic tx_en;
    logic [7:0] din;
    logic sout;
    logic busy_tx;

    uart_tx dut(fpga_clk, nrst, tx_en, din, sout, busy_tx);

    always begin
        fpga_clk = 1; #5;
        fpga_clk = 0; #5;
    end

    initial begin
        $dumpfile("uart_tx.vcd");
        $dumpvars(0, uart_tx_tb);
        nrst = 0;
        tx_en = 0;
        din = 8'h00;

        #22;
        nrst = 1;
        #7; 
        tx_en = 1;
        din = 8'hee;
        #700; tx_en = 0;

        #100; tx_en = 1;
        din = 8'h95;
        #1400; tx_en = 0;
        #200; tx_en = 1;
        din = 8'hf0;
        
        
    end
endmodule

sim/uart_tx.vcd
$date
	Fri Jun 06 12:03:15 2025
$end
$version
	ModelSim Version 2020.1
$end
$timescale
	1ns
$end

$scope module uart_tx_tb $end
$var reg 1 ! fpga_clk $end
$var reg 1 " nrst $end
$var reg 1 # tx_en $end
$var reg 8 $ din [7:0] $end
$var reg 1 % sout $end
$var reg 1 & busy_tx $end

$scope module dut $end
$var parameter 32 ' BAUDRATE $end
$var wire 1 ( fpga_clk $end
$var wire 1 ) nrst $end
$var wire 1 * tx_en $end
$var wire 1 + din [7] $end
$var wire 1 , din [6] $end
$var wire 1 - din [5] $end
$var wire 1 . din [4] $end
$var wire 1 / din [3] $end
$var wire 1 0 din [2] $end
$var wire 1 1 din [1] $end
$var wire 1 2 din [0] $end
$var reg 1 3 sout $end
$var reg 1 4 busy_tx $end
$var reg 2 5 cs [1:0] $end
$var reg 2 6 ns [1:0] $end
$var reg 16 7 tick_total [15:0] $end
$var reg 16 8 tick_cnt [15:0] $end
$var reg 9 9 dout [8:0] $end
$var reg 1 : tx_complete $end
$var reg 1 ; baud_clk $end
$var reg 1 < baud_edge $end
$var reg 1 = baud_edge_d1 $end
$var reg 1 > baud_edge_d2 $end
$var reg 1 ? load $end
$var reg 5 @ baud_cnt [4:0] $end
$var reg 1 A tx_en_d1 $end
$var reg 1 B tx_en_d2 $end
$var reg 1 C tx_en_posedge $end
$var wire 1 D sout_data $end
$upscope $end
$upscope $end
$enddefinitions $end
#0
$dumpvars
1!
0"
0#
b0 $
1%
x&
13
x4
b0 5
b0 6
b101 7
b0 8
b111111111 9
x:
0;
0<
0=
0>
0?
b0 @
0A
0B
0C
b11100001000000000 '
1D
1(
0)
0*
02
01
00
0/
0.
0-
0,
0+
$end
#5
0!
0(
#10
1!
1(
#15
0!
0(
#20
1!
1(
#22
1"
1)
#25
0!
0(
#29
1#
b11101110 $
11
10
1/
1-
1,
1+
1*
b1 6
#30
1!
1(
1A
b1 8
#35
0!
0(
#40
1!
1(
1C
1B
1?
b10 8
#45
0!
0(
#50
1!
1(
0C
0?
b11 8
b11101110 9
b1 5
0D
03
0%
#55
0!
0(
#60
1!
1(
b100 8
#65
0!
0(
#70
1!
1(
b101 8
#75
0!
0(
#80
1!
1(
1<
b0 8
1=
#85
0!
0(
#90
1!
1(
0<
b1 8
0=
1>
1;
b1 @
#95
0!
0(
#100
1!
1(
b10 8
0>
0;
b111011101 9
1D
13
1%
#105
0!
0(
#110
1!
1(
b11 8
#115
0!
0(
#120
1!
1(
b100 8
#125
0!
0(
#130
1!
1(
b101 8
#135
0!
0(
#140
1!
1(
1<
b0 8
1=
#145
0!
0(
#150
1!
1(
0<
b1 8
0=
1>
1;
b10 @
#155
0!
0(
#160
1!
1(
b10 8
0>
0;
b110111011 9
#165
0!
0(
#170
1!
1(
b11 8
#175
0!
0(
#180
1!
1(
b100 8
#185
0!
0(
#190
1!
1(
b101 8
#195
0!
0(
#200
1!
1(
1<
b0 8
1=
#205
0!
0(
#210
1!
1(
0<
b1 8
0=
1>
1;
b11 @
#215
0!
0(
#220
1!
1(
b10 8
0>
0;
b101110111 9
#225
0!
0(
#230
1!
1(
b11 8
#235
0!
0(
#240
1!
1(
b100 8
#245
0!
0(
#250
1!
1(
b101 8
#255
0!
0(
#260
1!
1(
1<
b0 8
1=
#265
0!
0(
#270
1!
1(
0<
b1 8
0=
1>
1;
b100 @
#275
0!
0(
#280
1!
1(
b10 8
0>
0;
b11101111 9
0D
03
0%
#285
0!
0(
#290
1!
1(
b11 8
#295
0!
0(
#300
1!
1(
b100 8
#305
0!
0(
#310
1!
1(
b101 8
#315
0!
0(
#320
1!
1(
1<
b0 8
1=
#325
0!
0(
#330
1!
1(
0<
b1 8
0=
1>
1;
b101 @
#335
0!
0(
#340
1!
1(
b10 8
0>
0;
b111011111 9
1D
13
1%
#345
0!
0(
#350
1!
1(
b11 8
#355
0!
0(
#360
1!
1(
b100 8
#365
0!
0(
#370
1!
1(
b101 8
#375
0!
0(
#380
1!
1(
1<
b0 8
1=
#385
0!
0(
#390
1!
1(
0<
b1 8
0=
1>
1;
b110 @
#395
0!
0(
#400
1!
1(
b10 8
0>
0;
b110111111 9
#405
0!
0(
#410
1!
1(
b11 8
#415
0!
0(
#420
1!
1(
b100 8
#425
0!
0(
#430
1!
1(
b101 8
#435
0!
0(
#440
1!
1(
1<
b0 8
1=
#445
0!
0(
#450
1!
1(
0<
b1 8
0=
1>
1;
b111 @
#455
0!
0(
#460
1!
1(
b10 8
0>
0;
b101111111 9
#465
0!
0(
#470
1!
1(
b11 8
#475
0!
0(
#480
1!
1(
b100 8
#485
0!
0(
#490
1!
1(
b101 8
#495
0!
0(
#500
1!
1(
1<
b0 8
1=
#505
0!
0(
#510
1!
1(
0<
b1 8
0=
1>
1;
b1000 @
#515
0!
0(
#520
1!
1(
b10 8
0>
0;
b11111111 9
0D
03
0%
#525
0!
0(
#530
1!
1(
b11 8
#535
0!
0(
#540
1!
1(
b100 8
#545
0!
0(
#550
1!
1(
b101 8
#555
0!
0(
#560
1!
1(
1<
b0 8
1=
#565
0!
0(
#570
1!
1(
0<
b1 8
0=
1>
1;
b1001 @
#575
0!
0(
#580
1!
1(
b10 8
0>
0;
b111111111 9
1D
13
1%
#585
0!
0(
#590
1!
1(
b11 8
#595
0!
0(
#600
1!
1(
b100 8
#605
0!
0(
#610
1!
1(
b101 8
#615
0!
0(
#620
1!
1(
1<
b0 8
1=
#625
0!
0(
#630
1!
1(
0<
b1 8
0=
1>
1;
b1010 @
#635
0!
0(
#640
1!
1(
b10 8
0>
b0 @
#645
0!
0(
#650
1!
1(
b11 8
0;
#655
0!
0(
#660
1!
1(
b100 8
#665
0!
0(
#670
1!
1(
b101 8
#675
0!
0(
#680
1!
1(
1<
b0 8
1=
#685
0!
0(
#690
1!
1(
0<
b1 8
0=
1>
1;
b1 @
#695
0!
0(
#700
1!
1(
b10 8
0>
0;
#705
0!
0(
#710
1!
1(
b11 8
#715
0!
0(
#720
1!
1(
b100 8
#725
0!
0(
#730
1!
1(
b101 8
#735
0!
0(
#740
1!
1(
1<
b0 8
1=
#745
0!
0(
#750
1!
1(
0<
b1 8
0=
1>
1;
b10 @
#755
0!
0(
#760
1!
1(
b10 8
0>
0;
#765
0!
0(
#770
1!
1(
b11 8
#775
0!
0(
#780
1!
1(
b100 8
#785
0!
0(
#790
1!
1(
b101 8
#795
0!
0(
#800
1!
1(
1<
b0 8
1=
#805
0!
0(
#810
1!
1(
0<
b1 8
0=
1>
1;
b11 @
#815
0!
0(
#820
1!
1(
b10 8
0>
0;
#825
0!
0(
#829
b10010101 $
12
01
0/
1.
0-
0,
#830
1!
1(
b11 8
#835
0!
0(
#840
1!
1(
b100 8
#845
0!
0(
#850
1!
1(
b101 8
#855
0!
0(
#860
1!
1(
1<
b0 8
1=
#865
0!
0(
#870
1!
1(
0<
b1 8
0=
1>
1;
b100 @
#875
0!
0(
#880
1!
1(
b10 8
0>
0;
#885
0!
0(
#890
1!
1(
b11 8
#895
0!
0(
#900
1!
1(
b100 8
#905
0!
0(
#910
1!
1(
b101 8
#915
0!
0(
#920
1!
1(
1<
b0 8
1=
#925
0!
0(
#930
1!
1(
0<
b1 8
0=
1>
1;
b101 @
#935
0!
0(
#940
1!
1(
b10 8
0>
0;
#945
0!
0(
#950
1!
1(
b11 8
#955
0!
0(
#960
1!
1(
b100 8
#965
0!
0(
#970
1!
1(
b101 8
#975
0!
0(
#980
1!
1(
1<
b0 8
1=
#985
0!
0(
#990
1!
1(
0<
b1 8
0=
1>
1;
b110 @
#995
0!
0(
#1000
1!
1(
b10 8
0>
0;
#1005
0!
0(
#1010
1!
1(
b11 8
#1015
0!
0(
#1020
1!
1(
b100 8
#1025
0!
0(
#1030
1!
1(
b101 8
#1035
0!
0(
#1040
1!
1(
1<
b0 8
1=
#1045
0!
0(
#1050
1!
1(
0<
b1 8
0=
1>
1;
b111 @
#1055
0!
0(
#1060
1!
1(
b10 8
0>
0;
#1065
0!
0(
#1070
1!
1(
b11 8
#1075
0!
0(
#1080
1!
1(
b100 8
#1085
0!
0(
#1090
1!
1(
b101 8
#1095
0!
0(
#1100
1!
1(
1<
b0 8
1=
#1105
0!
0(
#1110
1!
1(
0<
b1 8
0=
1>
1;
b1000 @
#1115
0!
0(
#1120
1!
1(
b10 8
0>
0;
#1125
0!
0(
#1130
1!
1(
b11 8
#1135
0!
0(
#1140
1!
1(
b100 8
#1145
0!
0(
#1150
1!
1(
b101 8
#1155
0!
0(
#1160
1!
1(
1<
b0 8
1=
#1165
0!
0(
#1170
1!
1(
0<
b1 8
0=
1>
1;
b1001 @
#1175
0!
0(
#1180
1!
1(
b10 8
0>
0;
#1185
0!
0(
#1190
1!
1(
b11 8
#1195
0!
0(
#1200
1!
1(
b100 8
#1205
0!
0(
#1210
1!
1(
b101 8
#1215
0!
0(
#1220
1!
1(
1<
b0 8
1=
#1225
0!
0(
#1230
1!
1(
0<
b1 8
0=
1>
1;
b1010 @
#1235
0!
0(
#1240
1!
1(
b10 8
0>
b0 @
#1245
0!
0(
#1250
1!
1(
b11 8
0;
#1255
0!
0(
#1260
1!
1(
b100 8
#1265
0!
0(
#1270
1!
1(
b101 8
#1275
0!
0(
#1280
1!
1(
1<
b0 8
1=
#1285
0!
0(
#1290
1!
1(
0<
b1 8
0=
1>
1;
b1 @
#1295
0!
0(
#1300
1!
1(
b10 8
0>
0;
#1305
0!
0(
#1310
1!
1(
b11 8
#1315
0!
0(
#1320
1!
1(
b100 8
#1325
0!
0(
#1330
1!
1(
b101 8
#1335
0!
0(
#1340
1!
1(
1<
b0 8
1=
#1345
0!
0(
#1350
1!
1(
0<
b1 8
0=
1>
1;
b10 @
#1355
0!
0(
#1360
1!
1(
b10 8
0>
0;
#1365
0!
0(
#1370
1!
1(
b11 8
#1375
0!
0(
#1380
1!
1(
b100 8
#1385
0!
0(
#1390
1!
1(
b101 8
#1395
0!
0(
#1400
1!
1(
1<
b0 8
1=
#1405
0!
0(
#1410
1!
1(
0<
b1 8
0=
1>
1;
b11 @
#1415
0!
0(
#1420
1!
1(
b10 8
0>
0;
#1425
0!
0(
#1430
1!
1(
b11 8
#1435
0!
0(
#1440
1!
1(
b100 8
#1445
0!
0(
#1450
1!
1(
b101 8
#1455
0!
0(
#1460
1!
1(
1<
b0 8
1=
#1465
0!
0(
#1470
1!
1(
0<
b1 8
0=
1>
1;
b100 @
#1475
0!
0(
#1480
1!
1(
b10 8
0>
0;
#1485
0!
0(
#1490
1!
1(
b11 8
#1495
0!
0(
#1500
1!
1(
b100 8
#1505
0!
0(
#1510
1!
1(
b101 8
#1515
0!
0(
#1520
1!
1(
1<
b0 8
1=
#1525
0!
0(
#1530
1!
1(
0<
b1 8
0=
1>
1;
b101 @
#1535
0!
0(
#1540
1!
1(
b10 8
0>
0;
#1545
0!
0(
#1550
1!
1(
b11 8
#1555
0!
0(
#1560
1!
1(
b100 8
#1565
0!
0(
#1570
1!
1(
b101 8
#1575
0!
0(
#1580
1!
1(
1<
b0 8
1=
#1585
0!
0(
#1590
1!
1(
0<
b1 8
0=
1>
1;
b110 @
#1595
0!
0(
#1600
1!
1(
b10 8
0>
0;
#1605
0!
0(
#1610
1!
1(
b11 8
#1615
0!
0(
#1620
1!
1(
b100 8
#1625
0!
0(
#1629
b1111000 $
02
00
1/
1-
1,
0+
#1630
1!
1(
b101 8
#1635
0!
0(
#1640
1!
1(
1<
b0 8
1=
#1645
0!
0(
#1650
1!
1(
0<
b1 8
0=
1>
1;
b111 @
#1655
0!
0(
#1660
1!
1(
b10 8
0>
0;
#1665
0!
0(
#1670
1!
1(
b11 8
#1675
0!
0(
#1680
1!
1(
b100 8
#1685
0!
0(
#1690
1!
1(
b101 8
#1695
0!
0(
#1700
1!
1(
1<
b0 8
1=
#1705
0!
0(
#1710
1!
1(
0<
b1 8
0=
1>
1;
b1000 @
#1715
0!
0(
#1720
1!
1(
b10 8
0>
0;
#1725
0!
0(
#1730
1!
1(
b11 8
#1735
0!
0(
#1740
1!
1(
b100 8
#1745
0!
0(
#1750
1!
1(
b101 8
#1755
0!
0(
#1760
1!
1(
1<
b0 8
1=
#1765
0!
0(
#1770
1!
1(
0<
b1 8
0=
1>
1;
b1001 @
#1775
0!
0(
#1780
1!
1(
b10 8
0>
0;
#1785
0!
0(
#1790
1!
1(
b11 8
#1795
0!
0(
#1800
1!
1(
b100 8
#1805
0!
0(
#1810
1!
1(
b101 8
#1815
0!
0(
#1820
1!
1(
1<
b0 8
1=
#1825
0!
0(
#1830
1!
1(
0<
b1 8
0=
1>
1;
b1010 @
#1835
0!
0(
#1840
1!
1(
b10 8
0>
b0 @
#1845
0!
0(
#1850
1!
1(
b11 8
0;
#1855
0!
0(
#1860
1!
1(
b100 8
#1865
0!
0(
#1870
1!
1(
b101 8
#1875
0!
0(
#1880
1!
1(
1<
b0 8
1=
#1885
0!
0(
#1890
1!
1(
0<
b1 8
0=
1>
1;
b1 @
#1895
0!
0(
#1900
1!
1(
b10 8
0>
0;
#1905
0!
0(
#1910
1!
1(
b11 8
#1915
0!
0(
#1920
1!
1(
b100 8
#1925
0!
0(
#1930
1!
1(
b101 8
#1935
0!
0(
#1940
1!
1(
1<
b0 8
1=
#1945
0!
0(
#1950
1!
1(
0<
b1 8
0=
1>
1;
b10 @
#1955
0!
0(
#1960
1!
1(
b10 8
0>
0;
#1965
0!
0(
#1970
1!
1(
b11 8
#1975
0!
0(
#1980
1!
1(
b100 8
#1985
0!
0(
#1990
1!
1(
b101 8
#1995
0!
0(
#2000
1!
1(
1<
b0 8
1=
#2005
0!
0(
#2010
1!
1(
0<
b1 8
0=
1>
1;
b11 @
#2015
0!
0(
#2020
1!
1(
b10 8
0>
0;
#2025
0!
0(
#2030
1!
1(
b11 8
#2035
0!
0(
#2040
1!
1(
b100 8
#2045
0!
0(
#2050
1!
1(
b101 8
#2055
0!
0(
#2060
1!
1(
1<
b0 8
1=
#2065
0!
0(
#2070
1!
1(
0<
b1 8
0=
1>
1;
b100 @
#2075
0!
0(
#2080
1!
1(
b10 8
0>
0;
#2085
0!
0(
#2090
1!
1(
b11 8
#2095
0!
0(
#2100
1!
1(
b100 8
#2105
0!
0(
#2110
1!
1(
b101 8
#2115
0!
0(
#2120
1!
1(
1<
b0 8
1=
#2125
0!
0(
#2130
1!
1(
0<
b1 8
0=
1>
1;
b101 @
#2135
0!
0(
#2140
1!
1(
b10 8
0>
0;
#2145
0!
0(
#2150
1!
1(
b11 8
#2155
0!
0(
#2160
1!
1(
b100 8
#2165
0!
0(
#2170
1!
1(
b101 8
#2175
0!
0(
#2180
1!
1(
1<
b0 8
1=
#2185
0!
0(
#2190
1!
1(
0<
b1 8
0=
1>
1;
b110 @
#2195
0!
0(
#2200
1!
1(
b10 8
0>
0;
#2205
0!
0(
#2210
1!
1(
b11 8
#2215
0!
0(
#2220
1!
1(
b100 8
#2225
0!
0(
#2230
1!
1(
b101 8
#2235
0!
0(
#2240
1!
1(
1<
b0 8
1=
#2245
0!
0(
#2250
1!
1(
0<
b1 8
0=
1>
1;
b111 @
#2255
0!
0(
#2260
1!
1(
b10 8
0>
0;
#2265
0!
0(
#2270
1!
1(
b11 8
#2275
0!
0(
#2280
1!
1(
b100 8
#2285
0!
0(
#2290
1!
1(
b101 8
#2295
0!
0(
#2300
1!
1(
1<
b0 8
1=
#2305
0!
0(
#2310
1!
1(
0<
b1 8
0=
1>
1;
b1000 @
#2315
0!
0(
#2320
1!
1(
b10 8
0>
0;
#2325
0!
0(
#2330
1!
1(
b11 8
#2335
0!
0(
#2340
1!
1(
b100 8
#2345
0!
0(
#2350
1!
1(
b101 8
#2355
0!
0(
#2360
1!
1(
1<
b0 8
1=
#2365
0!
0(
#2370
1!
1(
0<
b1 8
0=
1>
1;
b1001 @
#2375
0!
0(
#2380
1!
1(
b10 8
0>
0;
#2385
0!
0(
#2390
1!
1(
b11 8
#2395
0!
0(
#2400
1!
1(
b100 8
#2405
0!
0(
#2410
1!
1(
b101 8
#2415
0!
0(
#2420
1!
1(
1<
b0 8
1=
#2425
0!
0(
#2430
1!
1(
0<
b1 8
0=
1>
1;
b1010 @
#2435
0!
0(
#2440
1!
1(
b10 8
0>
b0 @
#2445
0!
0(
#2450
1!
1(
b11 8
0;
#2455
0!
0(
#2460
1!
1(
b100 8
#2465
0!
0(
#2470
1!
1(
b101 8
#2475
0!
0(
#2480
1!
1(
1<
b0 8
1=
#2485
0!
0(
#2490
1!
1(
0<
b1 8
0=
1>
1;
b1 @
#2495
0!
0(
#2500
1!
1(
b10 8
0>
0;
#2505
0!
0(
#2510
1!
1(
b11 8
#2515
0!
0(
#2520
1!
1(
b100 8
#2525
0!
0(
#2530
1!
1(
b101 8
#2535
0!
0(
#2540
1!
1(
1<
b0 8
1=
#2545
0!
0(
#2550
1!
1(
0<
b1 8
0=
1>
1;
b10 @
#2555
0!
0(
#2560
1!
1(
b10 8
0>
0;
#2565
0!
0(
#2570
1!
1(
b11 8
#2575
0!
0(
#2580
1!
1(
b100 8
#2585
0!
0(
#2590
1!
1(
b101 8
#2595
0!
0(
#2600
1!
1(
1<
b0 8
1=
#2605
0!
0(
#2610
1!
1(
0<
b1 8
0=
1>
1;
b11 @
#2615
0!
0(
#2620
1!
1(
b10 8
0>
0;
#2625
0!
0(
#2630
1!
1(
b11 8
#2635
0!
0(
#2640
1!
1(
b100 8
#2645
0!
0(
#2650
1!
1(
b101 8
#2655
0!
0(
#2660
1!
1(
1<
b0 8
1=
#2665
0!
0(
#2670
1!
1(
0<
b1 8
0=
1>
1;
b100 @
#2675
0!
0(
#2680
1!
1(
b10 8
0>
0;
#2685
0!
0(
#2690
1!
1(
b11 8
#2695
0!
0(
#2700
1!
1(
b100 8
#2705
0!
0(
#2710
1!
1(
b101 8
#2715
0!
0(
#2720
1!
1(
1<
b0 8
1=
#2725
0!
0(
#2730
1!
1(
0<
b1 8
0=
1>
1;
b101 @
#2735
0!
0(
#2740
1!
1(
b10 8
0>
0;
#2745
0!
0(
#2750
1!
1(
b11 8
#2755
0!
0(
#2760
1!
1(
b100 8
#2765
0!
0(
#2770
1!
1(
b101 8
#2775
0!
0(
#2780
1!
1(
1<
b0 8
1=
#2785
0!
0(
#2790
1!
1(
0<
b1 8
0=
1>
1;
b110 @
#2795
0!
0(
#2800
1!
1(
b10 8
0>
0;
#2805
0!
0(
#2810
1!
1(
b11 8
#2815
0!
0(
#2820
1!
1(
b100 8
#2825
0!
0(
#2830
1!
1(
b101 8
#2835
0!
0(
#2840
1!
1(
1<
b0 8
1=
#2845
0!
0(
#2850
1!
1(
0<
b1 8
0=
1>
1;
b111 @
#2855
0!
0(
#2860
1!
1(
b10 8
0>
0;
#2865
0!
0(
#2870
1!
1(
b11 8
#2875
0!
0(
#2880
1!
1(
b100 8
#2885
0!
0(
#2890
1!
1(
b101 8
#2895
0!
0(
#2900
1!
1(
1<
b0 8
1=
#2905
0!
0(
#2910
1!
1(
0<
b1 8
0=
1>
1;
b1000 @
#2915
0!
0(
#2920
1!
1(
b10 8
0>
0;
#2925
0!
0(
#2930
1!
1(
b11 8
#2935
0!
0(
#2940
1!
1(
b100 8
#2945
0!
0(
#2950
1!
1(
b101 8
#2955
0!
0(
#2960
1!
1(
1<
b0 8
1=
#2965
0!
0(
#2970
1!
1(
0<
b1 8
0=
1>
1;
b1001 @
#2975
0!
0(
#2980
1!
1(
b10 8
0>
0;
#2985
0!
0(
#2990
1!
1(
b11 8
#2995
0!
0(
#3000
1!
1(
b100 8
#3005
0!
0(
#3010
1!
1(
b101 8
#3015
0!
0(
#3020
1!
1(
1<
b0 8
1=
#3025
0!
0(
#3030
1!
1(
0<
b1 8
0=
1>
1;
b1010 @
#3035
0!
0(
#3040
1!
1(
b10 8
0>
b0 @
#3045
0!
0(
#3050
1!
1(
b11 8
0;
#3055
0!
0(
#3060
1!
1(
b100 8
#3065
0!
0(
#3070
1!
1(
b101 8
#3075
0!
0(
#3080
1!
1(
1<
b0 8
1=
#3085
0!
0(
#3090
1!
1(
0<
b1 8
0=
1>
1;
b1 @
#3095
0!
0(
#3100
1!
1(
b10 8
0>
0;
#3105
0!
0(
#3110
1!
1(
b11 8
#3115
0!
0(
#3120
1!
1(
b100 8
#3125
0!
0(
#3130
1!
1(
b101 8
#3135
0!
0(
#3140
1!
1(
1<
b0 8
1=
#3145
0!
0(
#3150
1!
1(
0<
b1 8
0=
1>
1;
b10 @
#3155
0!
0(
#3160
1!
1(
b10 8
0>
0;
#3165
0!
0(
#3170
1!
1(
b11 8
#3175
0!
0(
#3180
1!
1(
b100 8
#3185
0!
0(
#3190
1!
1(
b101 8
#3195
0!
0(
#3200
1!
1(
1<
b0 8
1=
#3205
0!
0(
#3210
1!
1(
0<
b1 8
0=
1>
1;
b11 @
#3215
0!
0(
#3220
1!
1(
b10 8
0>
0;
#3225
0!
0(
#3230
1!
1(
b11 8
#3235
0!
0(
#3240
1!
1(
b100 8
#3245
0!
0(
#3250
1!
1(
b101 8
#3255
0!
0(
#3260
1!
1(
1<
b0 8
1=
#3265
0!
0(
#3270
1!
1(
0<
b1 8
0=
1>
1;
b100 @
#3275
0!
0(
#3280
1!
1(
b10 8
0>
0;
#3285
0!
0(
#3290
1!
1(
b11 8
#3295
0!
0(
#3300
1!
1(
b100 8
#3305
0!
0(
#3310
1!
1(
b101 8
#3315
0!
0(
#3320
1!
1(
1<
b0 8
1=
#3325
0!
0(
#3330
1!
1(
0<
b1 8
0=
1>
1;
b101 @
#3335
0!
0(
#3340
1!
1(
b10 8
0>
0;
#3345
0!
0(
#3350
1!
1(
b11 8
#3355
0!
0(
#3360
1!
1(
b100 8
#3365
0!
0(
#3370
1!
1(
b101 8
#3375
0!
0(
#3380
1!
1(
1<
b0 8
1=
#3385
0!
0(
#3390
1!
1(
0<
b1 8
0=
1>
1;
b110 @
#3395
0!
0(
#3400
1!
1(
b10 8
0>
0;
#3405
0!
0(
#3410
1!
1(
b11 8
#3415
0!
0(
#3420
1!
1(
b100 8
#3425
0!
0(
#3430
1!
1(
b101 8
#3435
0!
0(
#3440
1!
1(
1<
b0 8
1=
#3445
0!
0(
#3450
1!
1(
0<
b1 8
0=
1>
1;
b111 @
#3455
0!
0(
#3460
1!
1(
b10 8
0>
0;
#3465
0!
0(
#3470
1!
1(
b11 8
#3475
0!
0(
#3480
1!
1(
b100 8
#3485
0!
0(
#3490
1!
1(
b101 8
#3495
0!
0(
#3500
1!
1(
1<
b0 8
1=
#3505
0!
0(
#3510
1!
1(
0<
b1 8
0=
1>
1;
b1000 @
#3515
0!
0(
#3520
1!
1(
b10 8
0>
0;
#3525
0!
0(
#3530
1!
1(
b11 8
#3535
0!
0(
#3540
1!
1(
b100 8
#3545
0!
0(
#3550
1!
1(
b101 8
#3555
0!
0(
#3560
1!
1(
1<
b0 8
1=
#3565
0!
0(
#3570
1!
1(
0<
b1 8
0=
1>
1;
b1001 @
#3575
0!
0(
#3580
1!
1(
b10 8
0>
0;
#3585
0!
0(
#3590
1!
1(
b11 8
#3595
0!
0(
#3600
1!
1(
b100 8
#3605
0!
0(
#3610
1!
1(
b101 8
#3615
0!
0(
#3620
1!
1(
1<
b0 8
1=
#3625
0!
0(
#3630
1!
1(
0<
b1 8
0=
1>
1;
b1010 @
#3635
0!
0(
#3640
1!
1(
b10 8
0>
b0 @
#3645
0!
0(
#3650
1!
1(
b11 8
0;
#3655
0!
0(
#3660
1!
1(
b100 8
#3665
0!
0(
#3670
1!
1(
b101 8
#3675
0!
0(
#3680
1!
1(
1<
b0 8
1=
#3685
0!
0(
#3690
1!
1(
0<
b1 8
0=
1>
1;
b1 @
#3695
0!
0(
#3700
1!
1(
b10 8
0>
0;
#3705
0!
0(
#3710
1!
1(
b11 8
#3715
0!
0(
#3720
1!
1(
b100 8
#3725
0!
0(
#3730
1!
1(
b101 8
#3735
0!
0(
#3740
1!
1(
1<
b0 8
1=
#3745
0!
0(
#3750
1!
1(
0<
b1 8
0=
1>
1;
b10 @
#3755
0!
0(
#3760
1!
1(
b10 8
0>
0;
#3765
0!
0(
#3770
1!
1(
b11 8
#3775
0!
0(
#3780
1!
1(
b100 8
#3785
0!
0(
#3790
1!
1(
b101 8
#3795
0!
0(
#3800
1!
1(
1<
b0 8
1=
#3805
0!
0(
#3810
1!
1(
0<
b1 8
0=
1>
1;
b11 @
#3815
0!
0(
#3820
1!
1(
b10 8
0>
0;
#3825
0!
0(
#3830
1!
1(
b11 8
#3835
0!
0(
#3840
1!
1(
b100 8
#3845
0!
0(
#3850
1!
1(
b101 8
#3855
0!
0(
#3860
1!
1(
1<
b0 8
1=
#3865
0!
0(
#3870
1!
1(
0<
b1 8
0=
1>
1;
b100 @
#3875
0!
0(
#3880
1!
1(
b10 8
0>
0;
#3885
0!
0(
#3890
1!
1(
b11 8
#3895
0!
0(
#3900
1!
1(
b100 8
#3905
0!
0(
#3910
1!
1(
b101 8
#3915
0!
0(
#3920
1!
1(
1<
b0 8
1=
#3925
0!
0(
#3930
1!
1(
0<
b1 8
0=
1>
1;
b101 @
#3935
0!
0(
#3940
1!
1(
b10 8
0>
0;
#3945
0!
0(
#3950
1!
1(
b11 8
#3955
0!
0(
#3960
1!
1(
b100 8
#3965
0!
0(
#3970
1!
1(
b101 8
#3975
0!
0(
#3980
1!
1(
1<
b0 8
1=
#3985
0!
0(
#3990
1!
1(
0<
b1 8
0=
1>
1;
b110 @
#3995
0!
0(
#4000
1!
1(
b10 8
0>
0;
#4005
0!
0(
#4010
1!
1(
b11 8
#4015
0!
0(
#4020
1!
1(
b100 8
#4025
0!
0(
#4030
1!
1(
b101 8
#4035
0!
0(
#4040
1!
1(
1<
b0 8
1=
#4045
0!
0(
